snowpiercer/__init__.py
snowpiercer/block.py
snowpiercer/blockchain.py
snowpiercer/transaction.py
snowpiercer-1.0.1.dist-info/LICENSE
snowpiercer-1.0.1.dist-info/METADATA
snowpiercer-1.0.1.dist-info/WHEEL
snowpiercer-1.0.1.dist-info/top_level.txt
snowpiercer-1.0.1.dist-info/RECORD
