Metadata-Version: 2.1
Name: snowpiercer
Version: 1.0.1
Summary: UNKNOWN
Home-page: https://github.com/snowpiercer/snowpiercer
Author: snowpiercer
Author-email: UNKNOWN
License: UNKNOWN
Platform: UNKNOWN
Requires-Dist: pycryptodome
